putput/__init__.py
putput/combiner.py
putput/expander.py
putput/joiner.py
putput/logger.py
putput/pipeline.py
putput/validator.py
putput/presets/__init__.py
putput/presets/displaCy.py
putput/presets/factory.py
putput/presets/iob2.py
putput/presets/luis.py
putput/presets/stochastic.py
putput-0.5.3.dist-info/LICENSE
putput-0.5.3.dist-info/METADATA
putput-0.5.3.dist-info/WHEEL
putput-0.5.3.dist-info/top_level.txt
putput-0.5.3.dist-info/RECORD
