Metadata-Version: 2.1
Name: putput
Version: 0.5.3
Summary: Generate labeled data for conversational AI.
Home-page: https://github.com/michaelperel/putput
Author: Michael Perel
Author-email: michaelsethperel@gmail.com
License: UNKNOWN
Platform: UNKNOWN
Classifier: Programming Language :: Python :: 3
Classifier: Programming Language :: Python :: 3.5
Classifier: Programming Language :: Python :: 3.6
Classifier: Programming Language :: Python :: 3.7
Classifier: License :: OSI Approved :: MIT License
Classifier: Operating System :: OS Independent
Requires-Python: >=3.5.*
Requires-Dist: pyyaml (==5.1)
Requires-Dist: tqdm (==4.31.1)
Requires-Dist: nltk (==3.4)
Provides-Extra: dev
Requires-Dist: pylint (==2.3.1) ; extra == 'dev'
Requires-Dist: codecov (==2.0.15) ; extra == 'dev'
Requires-Dist: mypy (==0.670) ; extra == 'dev'
Requires-Dist: pytest (==4.3.1) ; extra == 'dev'
Requires-Dist: pytest-cov (==2.6.1) ; extra == 'dev'
Requires-Dist: sphinx-rtd-theme (==0.4.3) ; extra == 'dev'
